{
  "id": "f206122d-e95b-4ec0-b322-c38c24e5ab80",
  "prevId": "00000000-0000-0000-0000-000000000000",
  "version": "7",
  "dialect": "postgresql",
  "tables": {
    "public.email_verification_tokens": {
      "name": "email_verification_tokens",
      "schema": "",
      "columns": {
        "id": {
          "name": "id",
          "type": "uuid",
          "primaryKey": true,
          "notNull": true,
          "default": "gen_random_uuid()"
        },
        "user_id": {
          "name": "user_id",
          "type": "uuid",
          "primaryKey": false,
          "notNull": true
        },
        "token": {
          "name": "token",
          "type": "varchar(255)",
          "primaryKey": false,
          "notNull": true
        },
        "email": {
          "name": "email",
          "type": "varchar(255)",
          "primaryKey": false,
          "notNull": true
        },
        "expires_at": {
          "name": "expires_at",
          "type": "timestamp with time zone",
          "primaryKey": false,
          "notNull": true
        },
        "is_used": {
          "name": "is_used",
          "type": "boolean",
          "primaryKey": false,
          "notNull": true,
          "default": false
        },
        "created_at": {
          "name": "created_at",
          "type": "timestamp with time zone",
          "primaryKey": false,
          "notNull": true,
          "default": "now()"
        }
      },
      "indexes": {
        "email_verification_token_idx": {
          "name": "email_verification_token_idx",
          "columns": [
            {
              "expression": "token",
              "isExpression": false,
              "asc": true,
              "nulls": "last"
            }
          ],
          "isUnique": false,
          "concurrently": false,
          "method": "btree",
          "with": {}
        },
        "email_verification_user_idx": {
          "name": "email_verification_user_idx",
          "columns": [
            {
              "expression": "user_id",
              "isExpression": false,
              "asc": true,
              "nulls": "last"
            }
          ],
          "isUnique": false,
          "concurrently": false,
          "method": "btree",
          "with": {}
        },
        "email_verification_expiry_idx": {
          "name": "email_verification_expiry_idx",
          "columns": [
            {
              "expression": "expires_at",
              "isExpression": false,
              "asc": true,
              "nulls": "last"
            }
          ],
          "isUnique": false,
          "concurrently": false,
          "method": "btree",
          "with": {}
        }
      },
      "foreignKeys": {
        "email_verification_tokens_user_id_users_id_fk": {
          "name": "email_verification_tokens_user_id_users_id_fk",
          "tableFrom": "email_verification_tokens",
          "tableTo": "users",
          "columnsFrom": [
            "user_id"
          ],
          "columnsTo": [
            "id"
          ],
          "onDelete": "cascade",
          "onUpdate": "no action"
        }
      },
      "compositePrimaryKeys": {},
      "uniqueConstraints": {
        "email_verification_tokens_token_unique": {
          "name": "email_verification_tokens_token_unique",
          "nullsNotDistinct": false,
          "columns": [
            "token"
          ]
        }
      },
      "policies": {},
      "checkConstraints": {},
      "isRLSEnabled": false
    },
    "public.oauth_accounts": {
      "name": "oauth_accounts",
      "schema": "",
      "columns": {
        "id": {
          "name": "id",
          "type": "uuid",
          "primaryKey": true,
          "notNull": true,
          "default": "gen_random_uuid()"
        },
        "user_id": {
          "name": "user_id",
          "type": "uuid",
          "primaryKey": false,
          "notNull": true
        },
        "provider": {
          "name": "provider",
          "type": "varchar(50)",
          "primaryKey": false,
          "notNull": true
        },
        "provider_user_id": {
          "name": "provider_user_id",
          "type": "varchar(255)",
          "primaryKey": false,
          "notNull": true
        },
        "access_token": {
          "name": "access_token",
          "type": "text",
          "primaryKey": false,
          "notNull": false
        },
        "refresh_token": {
          "name": "refresh_token",
          "type": "text",
          "primaryKey": false,
          "notNull": false
        },
        "token_expiry": {
          "name": "token_expiry",
          "type": "timestamp with time zone",
          "primaryKey": false,
          "notNull": false
        },
        "created_at": {
          "name": "created_at",
          "type": "timestamp with time zone",
          "primaryKey": false,
          "notNull": true,
          "default": "now()"
        },
        "updated_at": {
          "name": "updated_at",
          "type": "timestamp with time zone",
          "primaryKey": false,
          "notNull": true,
          "default": "now()"
        }
      },
      "indexes": {
        "oauth_provider_user_idx": {
          "name": "oauth_provider_user_idx",
          "columns": [
            {
              "expression": "provider",
              "isExpression": false,
              "asc": true,
              "nulls": "last"
            },
            {
              "expression": "provider_user_id",
              "isExpression": false,
              "asc": true,
              "nulls": "last"
            }
          ],
          "isUnique": false,
          "concurrently": false,
          "method": "btree",
          "with": {}
        },
        "oauth_user_idx": {
          "name": "oauth_user_idx",
          "columns": [
            {
              "expression": "user_id",
              "isExpression": false,
              "asc": true,
              "nulls": "last"
            }
          ],
          "isUnique": false,
          "concurrently": false,
          "method": "btree",
          "with": {}
        }
      },
      "foreignKeys": {
        "oauth_accounts_user_id_users_id_fk": {
          "name": "oauth_accounts_user_id_users_id_fk",
          "tableFrom": "oauth_accounts",
          "tableTo": "users",
          "columnsFrom": [
            "user_id"
          ],
          "columnsTo": [
            "id"
          ],
          "onDelete": "cascade",
          "onUpdate": "no action"
        }
      },
      "compositePrimaryKeys": {},
      "uniqueConstraints": {},
      "policies": {},
      "checkConstraints": {},
      "isRLSEnabled": false
    },
    "public.password_reset_tokens": {
      "name": "password_reset_tokens",
      "schema": "",
      "columns": {
        "id": {
          "name": "id",
          "type": "uuid",
          "primaryKey": true,
          "notNull": true,
          "default": "gen_random_uuid()"
        },
        "user_id": {
          "name": "user_id",
          "type": "uuid",
          "primaryKey": false,
          "notNull": true
        },
        "token": {
          "name": "token",
          "type": "varchar(255)",
          "primaryKey": false,
          "notNull": true
        },
        "expires_at": {
          "name": "expires_at",
          "type": "timestamp with time zone",
          "primaryKey": false,
          "notNull": true
        },
        "is_used": {
          "name": "is_used",
          "type": "boolean",
          "primaryKey": false,
          "notNull": true,
          "default": false
        },
        "created_at": {
          "name": "created_at",
          "type": "timestamp with time zone",
          "primaryKey": false,
          "notNull": true,
          "default": "now()"
        }
      },
      "indexes": {
        "password_reset_token_idx": {
          "name": "password_reset_token_idx",
          "columns": [
            {
              "expression": "token",
              "isExpression": false,
              "asc": true,
              "nulls": "last"
            }
          ],
          "isUnique": false,
          "concurrently": false,
          "method": "btree",
          "with": {}
        },
        "password_reset_user_idx": {
          "name": "password_reset_user_idx",
          "columns": [
            {
              "expression": "user_id",
              "isExpression": false,
              "asc": true,
              "nulls": "last"
            }
          ],
          "isUnique": false,
          "concurrently": false,
          "method": "btree",
          "with": {}
        },
        "password_reset_expiry_idx": {
          "name": "password_reset_expiry_idx",
          "columns": [
            {
              "expression": "expires_at",
              "isExpression": false,
              "asc": true,
              "nulls": "last"
            }
          ],
          "isUnique": false,
          "concurrently": false,
          "method": "btree",
          "with": {}
        }
      },
      "foreignKeys": {
        "password_reset_tokens_user_id_users_id_fk": {
          "name": "password_reset_tokens_user_id_users_id_fk",
          "tableFrom": "password_reset_tokens",
          "tableTo": "users",
          "columnsFrom": [
            "user_id"
          ],
          "columnsTo": [
            "id"
          ],
          "onDelete": "cascade",
          "onUpdate": "no action"
        }
      },
      "compositePrimaryKeys": {},
      "uniqueConstraints": {
        "password_reset_tokens_token_unique": {
          "name": "password_reset_tokens_token_unique",
          "nullsNotDistinct": false,
          "columns": [
            "token"
          ]
        }
      },
      "policies": {},
      "checkConstraints": {},
      "isRLSEnabled": false
    },
    "public.sessions": {
      "name": "sessions",
      "schema": "",
      "columns": {
        "id": {
          "name": "id",
          "type": "uuid",
          "primaryKey": true,
          "notNull": true,
          "default": "gen_random_uuid()"
        },
        "user_id": {
          "name": "user_id",
          "type": "uuid",
          "primaryKey": false,
          "notNull": true
        },
        "session_token": {
          "name": "session_token",
          "type": "varchar(255)",
          "primaryKey": false,
          "notNull": true
        },
        "refresh_token": {
          "name": "refresh_token",
          "type": "varchar(255)",
          "primaryKey": false,
          "notNull": true
        },
        "expires_at": {
          "name": "expires_at",
          "type": "timestamp with time zone",
          "primaryKey": false,
          "notNull": true
        },
        "refresh_expires_at": {
          "name": "refresh_expires_at",
          "type": "timestamp with time zone",
          "primaryKey": false,
          "notNull": true
        },
        "user_agent": {
          "name": "user_agent",
          "type": "text",
          "primaryKey": false,
          "notNull": false
        },
        "ip_address": {
          "name": "ip_address",
          "type": "varchar(45)",
          "primaryKey": false,
          "notNull": false
        },
        "created_at": {
          "name": "created_at",
          "type": "timestamp with time zone",
          "primaryKey": false,
          "notNull": true,
          "default": "now()"
        },
        "last_used_at": {
          "name": "last_used_at",
          "type": "timestamp with time zone",
          "primaryKey": false,
          "notNull": true,
          "default": "now()"
        }
      },
      "indexes": {
        "sessions_token_idx": {
          "name": "sessions_token_idx",
          "columns": [
            {
              "expression": "session_token",
              "isExpression": false,
              "asc": true,
              "nulls": "last"
            }
          ],
          "isUnique": false,
          "concurrently": false,
          "method": "btree",
          "with": {}
        },
        "sessions_refresh_token_idx": {
          "name": "sessions_refresh_token_idx",
          "columns": [
            {
              "expression": "refresh_token",
              "isExpression": false,
              "asc": true,
              "nulls": "last"
            }
          ],
          "isUnique": false,
          "concurrently": false,
          "method": "btree",
          "with": {}
        },
        "sessions_user_idx": {
          "name": "sessions_user_idx",
          "columns": [
            {
              "expression": "user_id",
              "isExpression": false,
              "asc": true,
              "nulls": "last"
            }
          ],
          "isUnique": false,
          "concurrently": false,
          "method": "btree",
          "with": {}
        },
        "sessions_expiry_idx": {
          "name": "sessions_expiry_idx",
          "columns": [
            {
              "expression": "expires_at",
              "isExpression": false,
              "asc": true,
              "nulls": "last"
            }
          ],
          "isUnique": false,
          "concurrently": false,
          "method": "btree",
          "with": {}
        }
      },
      "foreignKeys": {
        "sessions_user_id_users_id_fk": {
          "name": "sessions_user_id_users_id_fk",
          "tableFrom": "sessions",
          "tableTo": "users",
          "columnsFrom": [
            "user_id"
          ],
          "columnsTo": [
            "id"
          ],
          "onDelete": "cascade",
          "onUpdate": "no action"
        }
      },
      "compositePrimaryKeys": {},
      "uniqueConstraints": {
        "sessions_session_token_unique": {
          "name": "sessions_session_token_unique",
          "nullsNotDistinct": false,
          "columns": [
            "session_token"
          ]
        },
        "sessions_refresh_token_unique": {
          "name": "sessions_refresh_token_unique",
          "nullsNotDistinct": false,
          "columns": [
            "refresh_token"
          ]
        }
      },
      "policies": {},
      "checkConstraints": {},
      "isRLSEnabled": false
    },
    "public.user_preferences": {
      "name": "user_preferences",
      "schema": "",
      "columns": {
        "id": {
          "name": "id",
          "type": "uuid",
          "primaryKey": true,
          "notNull": true,
          "default": "gen_random_uuid()"
        },
        "user_id": {
          "name": "user_id",
          "type": "uuid",
          "primaryKey": false,
          "notNull": true
        },
        "email_notifications": {
          "name": "email_notifications",
          "type": "boolean",
          "primaryKey": false,
          "notNull": true,
          "default": true
        },
        "webhook_url": {
          "name": "webhook_url",
          "type": "varchar(500)",
          "primaryKey": false,
          "notNull": false
        },
        "timezone": {
          "name": "timezone",
          "type": "varchar(100)",
          "primaryKey": false,
          "notNull": true,
          "default": "'UTC'"
        },
        "created_at": {
          "name": "created_at",
          "type": "timestamp with time zone",
          "primaryKey": false,
          "notNull": true,
          "default": "now()"
        },
        "updated_at": {
          "name": "updated_at",
          "type": "timestamp with time zone",
          "primaryKey": false,
          "notNull": true,
          "default": "now()"
        }
      },
      "indexes": {
        "user_preferences_user_idx": {
          "name": "user_preferences_user_idx",
          "columns": [
            {
              "expression": "user_id",
              "isExpression": false,
              "asc": true,
              "nulls": "last"
            }
          ],
          "isUnique": false,
          "concurrently": false,
          "method": "btree",
          "with": {}
        }
      },
      "foreignKeys": {
        "user_preferences_user_id_users_id_fk": {
          "name": "user_preferences_user_id_users_id_fk",
          "tableFrom": "user_preferences",
          "tableTo": "users",
          "columnsFrom": [
            "user_id"
          ],
          "columnsTo": [
            "id"
          ],
          "onDelete": "cascade",
          "onUpdate": "no action"
        }
      },
      "compositePrimaryKeys": {},
      "uniqueConstraints": {
        "user_preferences_user_id_unique": {
          "name": "user_preferences_user_id_unique",
          "nullsNotDistinct": false,
          "columns": [
            "user_id"
          ]
        }
      },
      "policies": {},
      "checkConstraints": {},
      "isRLSEnabled": false
    },
    "public.users": {
      "name": "users",
      "schema": "",
      "columns": {
        "id": {
          "name": "id",
          "type": "uuid",
          "primaryKey": true,
          "notNull": true,
          "default": "gen_random_uuid()"
        },
        "email": {
          "name": "email",
          "type": "varchar(255)",
          "primaryKey": false,
          "notNull": true
        },
        "name": {
          "name": "name",
          "type": "varchar(100)",
          "primaryKey": false,
          "notNull": true
        },
        "password_hash": {
          "name": "password_hash",
          "type": "text",
          "primaryKey": false,
          "notNull": false
        },
        "google_id": {
          "name": "google_id",
          "type": "varchar(100)",
          "primaryKey": false,
          "notNull": false
        },
        "is_beta_user": {
          "name": "is_beta_user",
          "type": "boolean",
          "primaryKey": false,
          "notNull": true,
          "default": false
        },
        "email_verified": {
          "name": "email_verified",
          "type": "boolean",
          "primaryKey": false,
          "notNull": true,
          "default": false
        },
        "created_at": {
          "name": "created_at",
          "type": "timestamp with time zone",
          "primaryKey": false,
          "notNull": true,
          "default": "now()"
        },
        "updated_at": {
          "name": "updated_at",
          "type": "timestamp with time zone",
          "primaryKey": false,
          "notNull": true,
          "default": "now()"
        },
        "last_login_at": {
          "name": "last_login_at",
          "type": "timestamp with time zone",
          "primaryKey": false,
          "notNull": false
        }
      },
      "indexes": {
        "users_email_idx": {
          "name": "users_email_idx",
          "columns": [
            {
              "expression": "email",
              "isExpression": false,
              "asc": true,
              "nulls": "last"
            }
          ],
          "isUnique": false,
          "concurrently": false,
          "method": "btree",
          "with": {}
        },
        "users_google_id_idx": {
          "name": "users_google_id_idx",
          "columns": [
            {
              "expression": "google_id",
              "isExpression": false,
              "asc": true,
              "nulls": "last"
            }
          ],
          "isUnique": false,
          "concurrently": false,
          "method": "btree",
          "with": {}
        },
        "users_beta_user_idx": {
          "name": "users_beta_user_idx",
          "columns": [
            {
              "expression": "is_beta_user",
              "isExpression": false,
              "asc": true,
              "nulls": "last"
            }
          ],
          "isUnique": false,
          "concurrently": false,
          "method": "btree",
          "with": {}
        }
      },
      "foreignKeys": {},
      "compositePrimaryKeys": {},
      "uniqueConstraints": {
        "users_email_unique": {
          "name": "users_email_unique",
          "nullsNotDistinct": false,
          "columns": [
            "email"
          ]
        },
        "users_google_id_unique": {
          "name": "users_google_id_unique",
          "nullsNotDistinct": false,
          "columns": [
            "google_id"
          ]
        }
      },
      "policies": {},
      "checkConstraints": {},
      "isRLSEnabled": false
    },
    "public.fact_history": {
      "name": "fact_history",
      "schema": "",
      "columns": {
        "id": {
          "name": "id",
          "type": "uuid",
          "primaryKey": true,
          "notNull": true,
          "default": "gen_random_uuid()"
        },
        "monitor_id": {
          "name": "monitor_id",
          "type": "uuid",
          "primaryKey": false,
          "notNull": true
        },
        "value": {
          "name": "value",
          "type": "jsonb",
          "primaryKey": false,
          "notNull": true
        },
        "timestamp": {
          "name": "timestamp",
          "type": "timestamp with time zone",
          "primaryKey": false,
          "notNull": true
        },
        "triggered_alert": {
          "name": "triggered_alert",
          "type": "boolean",
          "primaryKey": false,
          "notNull": true,
          "default": false
        },
        "source": {
          "name": "source",
          "type": "varchar(500)",
          "primaryKey": false,
          "notNull": true
        },
        "change_type": {
          "name": "change_type",
          "type": "varchar(20)",
          "primaryKey": false,
          "notNull": false
        },
        "change_amount": {
          "name": "change_amount",
          "type": "numeric(15, 6)",
          "primaryKey": false,
          "notNull": false
        },
        "change_percentage": {
          "name": "change_percentage",
          "type": "numeric(5, 2)",
          "primaryKey": false,
          "notNull": false
        },
        "created_at": {
          "name": "created_at",
          "type": "timestamp with time zone",
          "primaryKey": false,
          "notNull": true,
          "default": "now()"
        }
      },
      "indexes": {
        "fact_history_monitor_timestamp_idx": {
          "name": "fact_history_monitor_timestamp_idx",
          "columns": [
            {
              "expression": "monitor_id",
              "isExpression": false,
              "asc": true,
              "nulls": "last"
            },
            {
              "expression": "timestamp",
              "isExpression": false,
              "asc": true,
              "nulls": "last"
            }
          ],
          "isUnique": false,
          "concurrently": false,
          "method": "btree",
          "with": {}
        },
        "fact_history_timestamp_idx": {
          "name": "fact_history_timestamp_idx",
          "columns": [
            {
              "expression": "timestamp",
              "isExpression": false,
              "asc": true,
              "nulls": "last"
            }
          ],
          "isUnique": false,
          "concurrently": false,
          "method": "btree",
          "with": {}
        },
        "fact_history_change_type_idx": {
          "name": "fact_history_change_type_idx",
          "columns": [
            {
              "expression": "change_type",
              "isExpression": false,
              "asc": true,
              "nulls": "last"
            }
          ],
          "isUnique": false,
          "concurrently": false,
          "method": "btree",
          "with": {}
        }
      },
      "foreignKeys": {
        "fact_history_monitor_id_monitors_id_fk": {
          "name": "fact_history_monitor_id_monitors_id_fk",
          "tableFrom": "fact_history",
          "tableTo": "monitors",
          "columnsFrom": [
            "monitor_id"
          ],
          "columnsTo": [
            "id"
          ],
          "onDelete": "cascade",
          "onUpdate": "no action"
        }
      },
      "compositePrimaryKeys": {},
      "uniqueConstraints": {},
      "policies": {},
      "checkConstraints": {},
      "isRLSEnabled": false
    },
    "public.monitor_evaluations": {
      "name": "monitor_evaluations",
      "schema": "",
      "columns": {
        "id": {
          "name": "id",
          "type": "uuid",
          "primaryKey": true,
          "notNull": true,
          "default": "gen_random_uuid()"
        },
        "monitor_id": {
          "name": "monitor_id",
          "type": "uuid",
          "primaryKey": false,
          "notNull": true
        },
        "job_id": {
          "name": "job_id",
          "type": "varchar(255)",
          "primaryKey": false,
          "notNull": false
        },
        "status": {
          "name": "status",
          "type": "varchar(20)",
          "primaryKey": false,
          "notNull": true,
          "default": "'pending'"
        },
        "started_at": {
          "name": "started_at",
          "type": "timestamp with time zone",
          "primaryKey": false,
          "notNull": false
        },
        "completed_at": {
          "name": "completed_at",
          "type": "timestamp with time zone",
          "primaryKey": false,
          "notNull": false
        },
        "processing_time_ms": {
          "name": "processing_time_ms",
          "type": "integer",
          "primaryKey": false,
          "notNull": false
        },
        "extracted_value": {
          "name": "extracted_value",
          "type": "jsonb",
          "primaryKey": false,
          "notNull": false
        },
        "triggered_alert": {
          "name": "triggered_alert",
          "type": "boolean",
          "primaryKey": false,
          "notNull": false,
          "default": false
        },
        "error_message": {
          "name": "error_message",
          "type": "text",
          "primaryKey": false,
          "notNull": false
        },
        "triggered_by": {
          "name": "triggered_by",
          "type": "varchar(50)",
          "primaryKey": false,
          "notNull": true
        },
        "user_agent": {
          "name": "user_agent",
          "type": "text",
          "primaryKey": false,
          "notNull": false
        },
        "ip_address": {
          "name": "ip_address",
          "type": "varchar(45)",
          "primaryKey": false,
          "notNull": false
        },
        "created_at": {
          "name": "created_at",
          "type": "timestamp with time zone",
          "primaryKey": false,
          "notNull": true,
          "default": "now()"
        }
      },
      "indexes": {
        "monitor_evaluations_monitor_idx": {
          "name": "monitor_evaluations_monitor_idx",
          "columns": [
            {
              "expression": "monitor_id",
              "isExpression": false,
              "asc": true,
              "nulls": "last"
            }
          ],
          "isUnique": false,
          "concurrently": false,
          "method": "btree",
          "with": {}
        },
        "monitor_evaluations_status_idx": {
          "name": "monitor_evaluations_status_idx",
          "columns": [
            {
              "expression": "status",
              "isExpression": false,
              "asc": true,
              "nulls": "last"
            }
          ],
          "isUnique": false,
          "concurrently": false,
          "method": "btree",
          "with": {}
        },
        "monitor_evaluations_job_id_idx": {
          "name": "monitor_evaluations_job_id_idx",
          "columns": [
            {
              "expression": "job_id",
              "isExpression": false,
              "asc": true,
              "nulls": "last"
            }
          ],
          "isUnique": false,
          "concurrently": false,
          "method": "btree",
          "with": {}
        },
        "monitor_evaluations_triggered_by_idx": {
          "name": "monitor_evaluations_triggered_by_idx",
          "columns": [
            {
              "expression": "triggered_by",
              "isExpression": false,
              "asc": true,
              "nulls": "last"
            }
          ],
          "isUnique": false,
          "concurrently": false,
          "method": "btree",
          "with": {}
        },
        "monitor_evaluations_created_at_idx": {
          "name": "monitor_evaluations_created_at_idx",
          "columns": [
            {
              "expression": "created_at",
              "isExpression": false,
              "asc": true,
              "nulls": "last"
            }
          ],
          "isUnique": false,
          "concurrently": false,
          "method": "btree",
          "with": {}
        }
      },
      "foreignKeys": {
        "monitor_evaluations_monitor_id_monitors_id_fk": {
          "name": "monitor_evaluations_monitor_id_monitors_id_fk",
          "tableFrom": "monitor_evaluations",
          "tableTo": "monitors",
          "columnsFrom": [
            "monitor_id"
          ],
          "columnsTo": [
            "id"
          ],
          "onDelete": "cascade",
          "onUpdate": "no action"
        }
      },
      "compositePrimaryKeys": {},
      "uniqueConstraints": {
        "monitor_evaluations_job_id_unique": {
          "name": "monitor_evaluations_job_id_unique",
          "nullsNotDistinct": false,
          "columns": [
            "job_id"
          ]
        }
      },
      "policies": {},
      "checkConstraints": {},
      "isRLSEnabled": false
    },
    "public.monitor_facts": {
      "name": "monitor_facts",
      "schema": "",
      "columns": {
        "id": {
          "name": "id",
          "type": "uuid",
          "primaryKey": true,
          "notNull": true,
          "default": "gen_random_uuid()"
        },
        "monitor_id": {
          "name": "monitor_id",
          "type": "uuid",
          "primaryKey": false,
          "notNull": true
        },
        "value": {
          "name": "value",
          "type": "jsonb",
          "primaryKey": false,
          "notNull": true
        },
        "extracted_at": {
          "name": "extracted_at",
          "type": "timestamp with time zone",
          "primaryKey": false,
          "notNull": true,
          "default": "now()"
        },
        "source": {
          "name": "source",
          "type": "varchar(500)",
          "primaryKey": false,
          "notNull": true
        },
        "processing_time_ms": {
          "name": "processing_time_ms",
          "type": "integer",
          "primaryKey": false,
          "notNull": true
        },
        "triggered_alert": {
          "name": "triggered_alert",
          "type": "boolean",
          "primaryKey": false,
          "notNull": true,
          "default": false
        },
        "change_from_previous": {
          "name": "change_from_previous",
          "type": "jsonb",
          "primaryKey": false,
          "notNull": false
        },
        "confidence": {
          "name": "confidence",
          "type": "numeric(3, 2)",
          "primaryKey": false,
          "notNull": true,
          "default": "'1.00'"
        },
        "errors": {
          "name": "errors",
          "type": "jsonb",
          "primaryKey": false,
          "notNull": false
        },
        "created_at": {
          "name": "created_at",
          "type": "timestamp with time zone",
          "primaryKey": false,
          "notNull": true,
          "default": "now()"
        }
      },
      "indexes": {
        "monitor_facts_monitor_idx": {
          "name": "monitor_facts_monitor_idx",
          "columns": [
            {
              "expression": "monitor_id",
              "isExpression": false,
              "asc": true,
              "nulls": "last"
            }
          ],
          "isUnique": false,
          "concurrently": false,
          "method": "btree",
          "with": {}
        },
        "monitor_facts_extracted_at_idx": {
          "name": "monitor_facts_extracted_at_idx",
          "columns": [
            {
              "expression": "extracted_at",
              "isExpression": false,
              "asc": true,
              "nulls": "last"
            }
          ],
          "isUnique": false,
          "concurrently": false,
          "method": "btree",
          "with": {}
        },
        "monitor_facts_triggered_alert_idx": {
          "name": "monitor_facts_triggered_alert_idx",
          "columns": [
            {
              "expression": "triggered_alert",
              "isExpression": false,
              "asc": true,
              "nulls": "last"
            }
          ],
          "isUnique": false,
          "concurrently": false,
          "method": "btree",
          "with": {}
        },
        "monitor_facts_source_idx": {
          "name": "monitor_facts_source_idx",
          "columns": [
            {
              "expression": "source",
              "isExpression": false,
              "asc": true,
              "nulls": "last"
            }
          ],
          "isUnique": false,
          "concurrently": false,
          "method": "btree",
          "with": {}
        }
      },
      "foreignKeys": {
        "monitor_facts_monitor_id_monitors_id_fk": {
          "name": "monitor_facts_monitor_id_monitors_id_fk",
          "tableFrom": "monitor_facts",
          "tableTo": "monitors",
          "columnsFrom": [
            "monitor_id"
          ],
          "columnsTo": [
            "id"
          ],
          "onDelete": "cascade",
          "onUpdate": "no action"
        }
      },
      "compositePrimaryKeys": {},
      "uniqueConstraints": {},
      "policies": {},
      "checkConstraints": {},
      "isRLSEnabled": false
    },
    "public.monitors": {
      "name": "monitors",
      "schema": "",
      "columns": {
        "id": {
          "name": "id",
          "type": "uuid",
          "primaryKey": true,
          "notNull": true,
          "default": "gen_random_uuid()"
        },
        "user_id": {
          "name": "user_id",
          "type": "uuid",
          "primaryKey": false,
          "notNull": true
        },
        "name": {
          "name": "name",
          "type": "varchar(100)",
          "primaryKey": false,
          "notNull": true
        },
        "prompt": {
          "name": "prompt",
          "type": "text",
          "primaryKey": false,
          "notNull": true
        },
        "type": {
          "name": "type",
          "type": "varchar(10)",
          "primaryKey": false,
          "notNull": true
        },
        "is_active": {
          "name": "is_active",
          "type": "boolean",
          "primaryKey": false,
          "notNull": true,
          "default": true
        },
        "extracted_fact": {
          "name": "extracted_fact",
          "type": "text",
          "primaryKey": false,
          "notNull": true
        },
        "trigger_condition": {
          "name": "trigger_condition",
          "type": "text",
          "primaryKey": false,
          "notNull": true
        },
        "fact_type": {
          "name": "fact_type",
          "type": "varchar(20)",
          "primaryKey": false,
          "notNull": true
        },
        "last_checked": {
          "name": "last_checked",
          "type": "timestamp with time zone",
          "primaryKey": false,
          "notNull": false
        },
        "current_value": {
          "name": "current_value",
          "type": "jsonb",
          "primaryKey": false,
          "notNull": false
        },
        "previous_value": {
          "name": "previous_value",
          "type": "jsonb",
          "primaryKey": false,
          "notNull": false
        },
        "trigger_count": {
          "name": "trigger_count",
          "type": "integer",
          "primaryKey": false,
          "notNull": true,
          "default": 0
        },
        "evaluation_count": {
          "name": "evaluation_count",
          "type": "integer",
          "primaryKey": false,
          "notNull": true,
          "default": 0
        },
        "last_manual_refresh": {
          "name": "last_manual_refresh",
          "type": "timestamp with time zone",
          "primaryKey": false,
          "notNull": false
        },
        "created_at": {
          "name": "created_at",
          "type": "timestamp with time zone",
          "primaryKey": false,
          "notNull": true,
          "default": "now()"
        },
        "updated_at": {
          "name": "updated_at",
          "type": "timestamp with time zone",
          "primaryKey": false,
          "notNull": true,
          "default": "now()"
        }
      },
      "indexes": {
        "monitors_user_idx": {
          "name": "monitors_user_idx",
          "columns": [
            {
              "expression": "user_id",
              "isExpression": false,
              "asc": true,
              "nulls": "last"
            }
          ],
          "isUnique": false,
          "concurrently": false,
          "method": "btree",
          "with": {}
        },
        "monitors_active_idx": {
          "name": "monitors_active_idx",
          "columns": [
            {
              "expression": "is_active",
              "isExpression": false,
              "asc": true,
              "nulls": "last"
            }
          ],
          "isUnique": false,
          "concurrently": false,
          "method": "btree",
          "with": {}
        },
        "monitors_type_idx": {
          "name": "monitors_type_idx",
          "columns": [
            {
              "expression": "type",
              "isExpression": false,
              "asc": true,
              "nulls": "last"
            }
          ],
          "isUnique": false,
          "concurrently": false,
          "method": "btree",
          "with": {}
        },
        "monitors_last_checked_idx": {
          "name": "monitors_last_checked_idx",
          "columns": [
            {
              "expression": "last_checked",
              "isExpression": false,
              "asc": true,
              "nulls": "last"
            }
          ],
          "isUnique": false,
          "concurrently": false,
          "method": "btree",
          "with": {}
        },
        "monitors_name_search_idx": {
          "name": "monitors_name_search_idx",
          "columns": [
            {
              "expression": "name",
              "isExpression": false,
              "asc": true,
              "nulls": "last"
            }
          ],
          "isUnique": false,
          "concurrently": false,
          "method": "btree",
          "with": {}
        }
      },
      "foreignKeys": {
        "monitors_user_id_users_id_fk": {
          "name": "monitors_user_id_users_id_fk",
          "tableFrom": "monitors",
          "tableTo": "users",
          "columnsFrom": [
            "user_id"
          ],
          "columnsTo": [
            "id"
          ],
          "onDelete": "cascade",
          "onUpdate": "no action"
        }
      },
      "compositePrimaryKeys": {},
      "uniqueConstraints": {},
      "policies": {},
      "checkConstraints": {},
      "isRLSEnabled": false
    },
    "public.rate_limits": {
      "name": "rate_limits",
      "schema": "",
      "columns": {
        "id": {
          "name": "id",
          "type": "uuid",
          "primaryKey": true,
          "notNull": true,
          "default": "gen_random_uuid()"
        },
        "user_id": {
          "name": "user_id",
          "type": "uuid",
          "primaryKey": false,
          "notNull": true
        },
        "limit_type": {
          "name": "limit_type",
          "type": "varchar(50)",
          "primaryKey": false,
          "notNull": true
        },
        "identifier": {
          "name": "identifier",
          "type": "varchar(255)",
          "primaryKey": false,
          "notNull": true
        },
        "count": {
          "name": "count",
          "type": "integer",
          "primaryKey": false,
          "notNull": true,
          "default": 1
        },
        "reset_at": {
          "name": "reset_at",
          "type": "timestamp with time zone",
          "primaryKey": false,
          "notNull": true
        },
        "created_at": {
          "name": "created_at",
          "type": "timestamp with time zone",
          "primaryKey": false,
          "notNull": true,
          "default": "now()"
        },
        "updated_at": {
          "name": "updated_at",
          "type": "timestamp with time zone",
          "primaryKey": false,
          "notNull": true,
          "default": "now()"
        }
      },
      "indexes": {
        "rate_limits_user_limit_idx": {
          "name": "rate_limits_user_limit_idx",
          "columns": [
            {
              "expression": "user_id",
              "isExpression": false,
              "asc": true,
              "nulls": "last"
            },
            {
              "expression": "limit_type",
              "isExpression": false,
              "asc": true,
              "nulls": "last"
            }
          ],
          "isUnique": false,
          "concurrently": false,
          "method": "btree",
          "with": {}
        },
        "rate_limits_identifier_limit_idx": {
          "name": "rate_limits_identifier_limit_idx",
          "columns": [
            {
              "expression": "identifier",
              "isExpression": false,
              "asc": true,
              "nulls": "last"
            },
            {
              "expression": "limit_type",
              "isExpression": false,
              "asc": true,
              "nulls": "last"
            }
          ],
          "isUnique": false,
          "concurrently": false,
          "method": "btree",
          "with": {}
        },
        "rate_limits_reset_at_idx": {
          "name": "rate_limits_reset_at_idx",
          "columns": [
            {
              "expression": "reset_at",
              "isExpression": false,
              "asc": true,
              "nulls": "last"
            }
          ],
          "isUnique": false,
          "concurrently": false,
          "method": "btree",
          "with": {}
        }
      },
      "foreignKeys": {
        "rate_limits_user_id_users_id_fk": {
          "name": "rate_limits_user_id_users_id_fk",
          "tableFrom": "rate_limits",
          "tableTo": "users",
          "columnsFrom": [
            "user_id"
          ],
          "columnsTo": [
            "id"
          ],
          "onDelete": "cascade",
          "onUpdate": "no action"
        }
      },
      "compositePrimaryKeys": {},
      "uniqueConstraints": {},
      "policies": {},
      "checkConstraints": {},
      "isRLSEnabled": false
    },
    "public.email_notifications": {
      "name": "email_notifications",
      "schema": "",
      "columns": {
        "id": {
          "name": "id",
          "type": "uuid",
          "primaryKey": true,
          "notNull": true,
          "default": "gen_random_uuid()"
        },
        "user_id": {
          "name": "user_id",
          "type": "uuid",
          "primaryKey": false,
          "notNull": true
        },
        "monitor_id": {
          "name": "monitor_id",
          "type": "uuid",
          "primaryKey": false,
          "notNull": false
        },
        "subject": {
          "name": "subject",
          "type": "varchar(255)",
          "primaryKey": false,
          "notNull": true
        },
        "html_content": {
          "name": "html_content",
          "type": "text",
          "primaryKey": false,
          "notNull": true
        },
        "plain_text_content": {
          "name": "plain_text_content",
          "type": "text",
          "primaryKey": false,
          "notNull": true
        },
        "sent_at": {
          "name": "sent_at",
          "type": "timestamp with time zone",
          "primaryKey": false,
          "notNull": true
        },
        "delivered_at": {
          "name": "delivered_at",
          "type": "timestamp with time zone",
          "primaryKey": false,
          "notNull": false
        },
        "opened_at": {
          "name": "opened_at",
          "type": "timestamp with time zone",
          "primaryKey": false,
          "notNull": false
        },
        "clicked_at": {
          "name": "clicked_at",
          "type": "timestamp with time zone",
          "primaryKey": false,
          "notNull": false
        },
        "sendgrid_message_id": {
          "name": "sendgrid_message_id",
          "type": "varchar(255)",
          "primaryKey": false,
          "notNull": false
        },
        "delivery_status": {
          "name": "delivery_status",
          "type": "varchar(20)",
          "primaryKey": false,
          "notNull": true,
          "default": "'sent'"
        },
        "trigger_value": {
          "name": "trigger_value",
          "type": "jsonb",
          "primaryKey": false,
          "notNull": false
        },
        "previous_value": {
          "name": "previous_value",
          "type": "jsonb",
          "primaryKey": false,
          "notNull": false
        },
        "change_detected": {
          "name": "change_detected",
          "type": "boolean",
          "primaryKey": false,
          "notNull": true,
          "default": false
        },
        "notification_type": {
          "name": "notification_type",
          "type": "varchar(50)",
          "primaryKey": false,
          "notNull": true,
          "default": "'monitor_trigger'"
        },
        "created_at": {
          "name": "created_at",
          "type": "timestamp with time zone",
          "primaryKey": false,
          "notNull": true,
          "default": "now()"
        }
      },
      "indexes": {
        "email_notifications_user_idx": {
          "name": "email_notifications_user_idx",
          "columns": [
            {
              "expression": "user_id",
              "isExpression": false,
              "asc": true,
              "nulls": "last"
            }
          ],
          "isUnique": false,
          "concurrently": false,
          "method": "btree",
          "with": {}
        },
        "email_notifications_monitor_idx": {
          "name": "email_notifications_monitor_idx",
          "columns": [
            {
              "expression": "monitor_id",
              "isExpression": false,
              "asc": true,
              "nulls": "last"
            }
          ],
          "isUnique": false,
          "concurrently": false,
          "method": "btree",
          "with": {}
        },
        "email_notifications_sent_at_idx": {
          "name": "email_notifications_sent_at_idx",
          "columns": [
            {
              "expression": "sent_at",
              "isExpression": false,
              "asc": true,
              "nulls": "last"
            }
          ],
          "isUnique": false,
          "concurrently": false,
          "method": "btree",
          "with": {}
        },
        "email_notifications_delivery_status_idx": {
          "name": "email_notifications_delivery_status_idx",
          "columns": [
            {
              "expression": "delivery_status",
              "isExpression": false,
              "asc": true,
              "nulls": "last"
            }
          ],
          "isUnique": false,
          "concurrently": false,
          "method": "btree",
          "with": {}
        },
        "email_notifications_sendgrid_id_idx": {
          "name": "email_notifications_sendgrid_id_idx",
          "columns": [
            {
              "expression": "sendgrid_message_id",
              "isExpression": false,
              "asc": true,
              "nulls": "last"
            }
          ],
          "isUnique": false,
          "concurrently": false,
          "method": "btree",
          "with": {}
        },
        "email_notifications_type_idx": {
          "name": "email_notifications_type_idx",
          "columns": [
            {
              "expression": "notification_type",
              "isExpression": false,
              "asc": true,
              "nulls": "last"
            }
          ],
          "isUnique": false,
          "concurrently": false,
          "method": "btree",
          "with": {}
        }
      },
      "foreignKeys": {
        "email_notifications_user_id_users_id_fk": {
          "name": "email_notifications_user_id_users_id_fk",
          "tableFrom": "email_notifications",
          "tableTo": "users",
          "columnsFrom": [
            "user_id"
          ],
          "columnsTo": [
            "id"
          ],
          "onDelete": "cascade",
          "onUpdate": "no action"
        },
        "email_notifications_monitor_id_monitors_id_fk": {
          "name": "email_notifications_monitor_id_monitors_id_fk",
          "tableFrom": "email_notifications",
          "tableTo": "monitors",
          "columnsFrom": [
            "monitor_id"
          ],
          "columnsTo": [
            "id"
          ],
          "onDelete": "cascade",
          "onUpdate": "no action"
        }
      },
      "compositePrimaryKeys": {},
      "uniqueConstraints": {
        "email_notifications_sendgrid_message_id_unique": {
          "name": "email_notifications_sendgrid_message_id_unique",
          "nullsNotDistinct": false,
          "columns": [
            "sendgrid_message_id"
          ]
        }
      },
      "policies": {},
      "checkConstraints": {},
      "isRLSEnabled": false
    },
    "public.email_templates": {
      "name": "email_templates",
      "schema": "",
      "columns": {
        "id": {
          "name": "id",
          "type": "uuid",
          "primaryKey": true,
          "notNull": true,
          "default": "gen_random_uuid()"
        },
        "name": {
          "name": "name",
          "type": "varchar(100)",
          "primaryKey": false,
          "notNull": true
        },
        "version": {
          "name": "version",
          "type": "varchar(20)",
          "primaryKey": false,
          "notNull": true,
          "default": "'1.0.0'"
        },
        "subject": {
          "name": "subject",
          "type": "varchar(255)",
          "primaryKey": false,
          "notNull": true
        },
        "html_template": {
          "name": "html_template",
          "type": "text",
          "primaryKey": false,
          "notNull": true
        },
        "plain_text_template": {
          "name": "plain_text_template",
          "type": "text",
          "primaryKey": false,
          "notNull": true
        },
        "description": {
          "name": "description",
          "type": "text",
          "primaryKey": false,
          "notNull": false
        },
        "variables": {
          "name": "variables",
          "type": "jsonb",
          "primaryKey": false,
          "notNull": true
        },
        "is_active": {
          "name": "is_active",
          "type": "boolean",
          "primaryKey": false,
          "notNull": true,
          "default": true
        },
        "created_at": {
          "name": "created_at",
          "type": "timestamp with time zone",
          "primaryKey": false,
          "notNull": true,
          "default": "now()"
        },
        "updated_at": {
          "name": "updated_at",
          "type": "timestamp with time zone",
          "primaryKey": false,
          "notNull": true,
          "default": "now()"
        }
      },
      "indexes": {
        "email_templates_name_idx": {
          "name": "email_templates_name_idx",
          "columns": [
            {
              "expression": "name",
              "isExpression": false,
              "asc": true,
              "nulls": "last"
            }
          ],
          "isUnique": false,
          "concurrently": false,
          "method": "btree",
          "with": {}
        },
        "email_templates_active_idx": {
          "name": "email_templates_active_idx",
          "columns": [
            {
              "expression": "is_active",
              "isExpression": false,
              "asc": true,
              "nulls": "last"
            }
          ],
          "isUnique": false,
          "concurrently": false,
          "method": "btree",
          "with": {}
        }
      },
      "foreignKeys": {},
      "compositePrimaryKeys": {},
      "uniqueConstraints": {
        "email_templates_name_unique": {
          "name": "email_templates_name_unique",
          "nullsNotDistinct": false,
          "columns": [
            "name"
          ]
        }
      },
      "policies": {},
      "checkConstraints": {},
      "isRLSEnabled": false
    },
    "public.email_unsubscribes": {
      "name": "email_unsubscribes",
      "schema": "",
      "columns": {
        "id": {
          "name": "id",
          "type": "uuid",
          "primaryKey": true,
          "notNull": true,
          "default": "gen_random_uuid()"
        },
        "user_id": {
          "name": "user_id",
          "type": "uuid",
          "primaryKey": false,
          "notNull": true
        },
        "email": {
          "name": "email",
          "type": "varchar(255)",
          "primaryKey": false,
          "notNull": true
        },
        "unsubscribe_token": {
          "name": "unsubscribe_token",
          "type": "varchar(255)",
          "primaryKey": false,
          "notNull": true
        },
        "notification_type": {
          "name": "notification_type",
          "type": "varchar(50)",
          "primaryKey": false,
          "notNull": false,
          "default": "'all'"
        },
        "unsubscribed_at": {
          "name": "unsubscribed_at",
          "type": "timestamp with time zone",
          "primaryKey": false,
          "notNull": true,
          "default": "now()"
        },
        "user_agent": {
          "name": "user_agent",
          "type": "text",
          "primaryKey": false,
          "notNull": false
        },
        "ip_address": {
          "name": "ip_address",
          "type": "varchar(45)",
          "primaryKey": false,
          "notNull": false
        },
        "created_at": {
          "name": "created_at",
          "type": "timestamp with time zone",
          "primaryKey": false,
          "notNull": true,
          "default": "now()"
        }
      },
      "indexes": {
        "email_unsubscribes_user_idx": {
          "name": "email_unsubscribes_user_idx",
          "columns": [
            {
              "expression": "user_id",
              "isExpression": false,
              "asc": true,
              "nulls": "last"
            }
          ],
          "isUnique": false,
          "concurrently": false,
          "method": "btree",
          "with": {}
        },
        "email_unsubscribes_token_idx": {
          "name": "email_unsubscribes_token_idx",
          "columns": [
            {
              "expression": "unsubscribe_token",
              "isExpression": false,
              "asc": true,
              "nulls": "last"
            }
          ],
          "isUnique": false,
          "concurrently": false,
          "method": "btree",
          "with": {}
        },
        "email_unsubscribes_email_type_idx": {
          "name": "email_unsubscribes_email_type_idx",
          "columns": [
            {
              "expression": "email",
              "isExpression": false,
              "asc": true,
              "nulls": "last"
            },
            {
              "expression": "notification_type",
              "isExpression": false,
              "asc": true,
              "nulls": "last"
            }
          ],
          "isUnique": false,
          "concurrently": false,
          "method": "btree",
          "with": {}
        }
      },
      "foreignKeys": {
        "email_unsubscribes_user_id_users_id_fk": {
          "name": "email_unsubscribes_user_id_users_id_fk",
          "tableFrom": "email_unsubscribes",
          "tableTo": "users",
          "columnsFrom": [
            "user_id"
          ],
          "columnsTo": [
            "id"
          ],
          "onDelete": "cascade",
          "onUpdate": "no action"
        }
      },
      "compositePrimaryKeys": {},
      "uniqueConstraints": {
        "email_unsubscribes_unsubscribe_token_unique": {
          "name": "email_unsubscribes_unsubscribe_token_unique",
          "nullsNotDistinct": false,
          "columns": [
            "unsubscribe_token"
          ]
        }
      },
      "policies": {},
      "checkConstraints": {},
      "isRLSEnabled": false
    },
    "public.email_webhooks": {
      "name": "email_webhooks",
      "schema": "",
      "columns": {
        "id": {
          "name": "id",
          "type": "uuid",
          "primaryKey": true,
          "notNull": true,
          "default": "gen_random_uuid()"
        },
        "sendgrid_message_id": {
          "name": "sendgrid_message_id",
          "type": "varchar(255)",
          "primaryKey": false,
          "notNull": false
        },
        "event_type": {
          "name": "event_type",
          "type": "varchar(50)",
          "primaryKey": false,
          "notNull": true
        },
        "timestamp": {
          "name": "timestamp",
          "type": "timestamp with time zone",
          "primaryKey": false,
          "notNull": true
        },
        "payload": {
          "name": "payload",
          "type": "jsonb",
          "primaryKey": false,
          "notNull": true
        },
        "processed": {
          "name": "processed",
          "type": "boolean",
          "primaryKey": false,
          "notNull": true,
          "default": false
        },
        "processed_at": {
          "name": "processed_at",
          "type": "timestamp with time zone",
          "primaryKey": false,
          "notNull": false
        },
        "error_message": {
          "name": "error_message",
          "type": "text",
          "primaryKey": false,
          "notNull": false
        },
        "created_at": {
          "name": "created_at",
          "type": "timestamp with time zone",
          "primaryKey": false,
          "notNull": true,
          "default": "now()"
        }
      },
      "indexes": {
        "email_webhooks_message_id_idx": {
          "name": "email_webhooks_message_id_idx",
          "columns": [
            {
              "expression": "sendgrid_message_id",
              "isExpression": false,
              "asc": true,
              "nulls": "last"
            }
          ],
          "isUnique": false,
          "concurrently": false,
          "method": "btree",
          "with": {}
        },
        "email_webhooks_event_type_idx": {
          "name": "email_webhooks_event_type_idx",
          "columns": [
            {
              "expression": "event_type",
              "isExpression": false,
              "asc": true,
              "nulls": "last"
            }
          ],
          "isUnique": false,
          "concurrently": false,
          "method": "btree",
          "with": {}
        },
        "email_webhooks_processed_idx": {
          "name": "email_webhooks_processed_idx",
          "columns": [
            {
              "expression": "processed",
              "isExpression": false,
              "asc": true,
              "nulls": "last"
            }
          ],
          "isUnique": false,
          "concurrently": false,
          "method": "btree",
          "with": {}
        },
        "email_webhooks_timestamp_idx": {
          "name": "email_webhooks_timestamp_idx",
          "columns": [
            {
              "expression": "timestamp",
              "isExpression": false,
              "asc": true,
              "nulls": "last"
            }
          ],
          "isUnique": false,
          "concurrently": false,
          "method": "btree",
          "with": {}
        }
      },
      "foreignKeys": {},
      "compositePrimaryKeys": {},
      "uniqueConstraints": {},
      "policies": {},
      "checkConstraints": {},
      "isRLSEnabled": false
    }
  },
  "enums": {},
  "schemas": {},
  "sequences": {},
  "roles": {},
  "policies": {},
  "views": {},
  "_meta": {
    "columns": {},
    "schemas": {},
    "tables": {}
  }
}